near_py_builder
