Metadata-Version: 2.2
Name: near-py-builder
Version: 0.1.0
Summary: Add your description here
Requires-Python: >=3.13
Requires-Dist: typer
